Metadata-Version: 2.4
Name: floyd-pr-generator
Version: 0.2.2
Summary: Add your description here
Requires-Python: >=3.14
Requires-Dist: setuptools>=80.10.2
Requires-Dist: rich>=13.0.0
Requires-Dist: questionary>=2.1.1
Requires-Dist: pathlib>=1.0.1
Requires-Dist: pydantic>=2.12.5
Requires-Dist: pydantic-settings>=2.12.0
